{"images/icon_alarm_level_high.png":["images/icon_alarm_level_high.png"],"images/icon_alarm_level_low.png":["images/icon_alarm_level_low.png"],"images/icon_alarm_level_middle.png":["images/icon_alarm_level_middle.png"],"images/icon_baojing_bg.png":["images/icon_baojing_bg.png"],"images/icon_baojing_label.png":["images/icon_baojing_label.png"],"images/icon_yujing_bg.png":["images/icon_yujing_bg.png"],"images/icon_yujing_label.png":["images/icon_yujing_label.png"],"images/iphone_bg.png":["images/iphone_bg.png"],"images/lab_bj.png":["images/lab_bj.png"],"packages/cupertino_icons/assets/CupertinoIcons.ttf":["packages/cupertino_icons/assets/CupertinoIcons.ttf"]}